{"bones":[{"name":"root"},{"name":"pelvis","parent":"root","x":1,"y":30.66},{"name":"left_upper_leg","parent":"pelvis","length":8.33,"x":0.45,"y":-0.68,"rotation":-65.82},{"name":"neck","parent":"pelvis","x":1.6,"y":29.43},{"name":"right_upper_leg","parent":"pelvis","length":8.88,"x":-4.59,"y":-0.68,"rotation":-100.34},{"name":"torso","parent":"pelvis","x":2.03,"y":10.27},{"name":"head","parent":"neck","x":1.37,"y":10.11},{"name":"left_arm","parent":"neck","length":17.34,"x":0.45,"y":-4.59,"rotation":-75.43},{"name":"left_lower_leg","parent":"left_upper_leg","length":14.48,"x":8.87,"y":-0.45,"rotation":-34.1},{"name":"right_arm","parent":"neck","length":21.82,"x":-4.82,"y":-2.06,"rotation":-118.86},{"name":"right_lower_leg","parent":"right_upper_leg","length":16.49,"x":8.1,"y":-0.86,"rotation":2.25},{"name":"left_foot","parent":"left_lower_leg","length":13.55,"x":14.62,"y":0.45,"rotation":85.46},{"name":"left_hand","parent":"left_arm","length":20.95,"x":16.96,"y":0.34,"rotation":56.51},{"name":"right_foot","parent":"right_lower_leg","length":14.76,"x":16.62,"y":-0.89,"rotation":93.6},{"name":"right_hand","parent":"right_arm","length":21.6,"x":21.71,"y":0.14,"rotation":92.27}],"slots":[{"name":"left_upper_arm","bone":"left_arm","attachment":"left_upper_arm"},{"name":"left_lower_arm","bone":"left_hand","attachment":"left_lower_arm"},{"name":"left_leg","bone":"left_lower_leg","attachment":"left_leg"},{"name":"left_foot","bone":"left_foot","attachment":"left_foot"},{"name":"neck","bone":"neck","attachment":"neck"},{"name":"right_leg","bone":"right_lower_leg","attachment":"right_leg"},{"name":"right_foot","bone":"right_foot","attachment":"right_foot"},{"name":"torso","bone":"torso","attachment":"torso"},{"name":"head","bone":"head","attachment":"head"},{"name":"right_upper_arm","bone":"right_arm","attachment":"right_upper_arm"},{"name":"right_lower_arm","bone":"right_hand","attachment":"right_lower_arm"}],"skins":{"default":{"head":{"head":{"x":-2.24,"y":18.96,"width":58,"height":64}},"left_foot":{"left_foot":{"x":5.46,"y":1.01,"rotation":14.47,"width":28,"height":16}},"left_leg":{"left_leg":{"x":5.83,"y":-0.8,"rotation":101.96,"width":11,"height":21}},"left_lower_arm":{"left_lower_arm":{"x":11.58,"y":-0.8,"rotation":30.38,"width":26,"height":16}},"left_upper_arm":{"left_upper_arm":{"x":7.99,"y":0.06,"rotation":118.84,"width":17,"height":22}},"neck":{"neck":{"x":2.41,"y":4.29,"width":15,"height":22}},"right_foot":{"right_foot":{"x":6.35,"y":1.5,"rotation":4.48,"width":28,"height":16}},"right_leg":{"right_leg":{"x":6.89,"y":-0.36,"rotation":101.95,"width":11,"height":21}},"right_lower_arm":{"right_lower_arm":{"x":11.86,"y":-0.8,"rotation":26.59,"width":26,"height":16}},"right_upper_arm":{"right_upper_arm":{"x":12.4,"y":1.18,"rotation":127.97,"width":17,"height":22}},"torso":{"torso":{"x":-0.73,"y":2.06,"scaleX":0.98,"rotation":4.19,"width":40,"height":45}}}},"animations":{"fall":{"bones":{"pelvis":{"translate":[{"time":0,"x":0,"y":6,"curve":"stepped"},{"time":0.3333,"x":0,"y":6,"curve":"stepped"},{"time":0.6666,"x":0,"y":6,"curve":"stepped"},{"time":1,"x":0,"y":6}]},"right_foot":{"rotate":[{"time":0,"angle":-25.45,"curve":"stepped"},{"time":0.3333,"angle":-25.45,"curve":"stepped"},{"time":0.6666,"angle":-25.45,"curve":"stepped"},{"time":1,"angle":-25.45}]},"left_lower_leg":{"rotate":[{"time":0,"angle":8.42},{"time":0.1666,"angle":22.5},{"time":0.3333,"angle":8.42},{"time":0.5,"angle":22.5},{"time":0.6666,"angle":8.42},{"time":0.8333,"angle":22.5},{"time":1,"angle":8.42}]},"left_foot":{"rotate":[{"time":0,"angle":-15.25,"curve":"stepped"},{"time":0.3333,"angle":-15.25,"curve":"stepped"},{"time":0.6666,"angle":-15.25,"curve":"stepped"},{"time":1,"angle":-15.25}]},"right_lower_leg":{"rotate":[{"time":0,"angle":-11.15},{"time":0.1666,"angle":-29.85},{"time":0.3333,"angle":-11.15},{"time":0.5,"angle":-29.85},{"time":0.6666,"angle":-11.15},{"time":0.8333,"angle":-29.85},{"time":1,"angle":-11.15}]},"right_arm":{"rotate":[{"time":0,"angle":256.82},{"time":0.1666,"angle":246.7},{"time":0.3333,"angle":256.82},{"time":0.5,"angle":246.7},{"time":0.6666,"angle":256.82},{"time":0.8333,"angle":246.7},{"time":1,"angle":256.82}]},"right_hand":{"rotate":[{"time":0,"angle":-123.6,"curve":"stepped"},{"time":0.3333,"angle":-123.6,"curve":"stepped"},{"time":0.6666,"angle":-123.6,"curve":"stepped"},{"time":1,"angle":-123.6}]},"left_arm":{"rotate":[{"time":0,"angle":98.13},{"time":0.1666,"angle":88.78},{"time":0.3333,"angle":98.13},{"time":0.5,"angle":88.78},{"time":0.6666,"angle":98.13},{"time":0.8333,"angle":88.78},{"time":1,"angle":98.13}]},"left_hand":{"rotate":[{"time":0,"angle":-12.73,"curve":"stepped"},{"time":0.3333,"angle":-12.73,"curve":"stepped"},{"time":0.6666,"angle":-12.73,"curve":"stepped"},{"time":1,"angle":-12.73}]},"right_upper_leg":{"rotate":[{"time":0.1666,"angle":5.42,"curve":"stepped"},{"time":0.5,"angle":5.42,"curve":"stepped"},{"time":0.8333,"angle":5.42}]}}},"idle":{"bones":{"root":{"rotate":[{"time":0,"angle":0,"curve":"stepped"},{"time":1.1666,"angle":0}],"translate":[{"time":0,"x":0,"y":0,"curve":"stepped"},{"time":1.1666,"x":0,"y":0}],"scale":[{"time":0,"x":1,"y":1,"curve":"stepped"},{"time":1.1666,"x":1,"y":1}]},"pelvis":{"rotate":[{"time":0,"angle":0,"curve":"stepped"},{"time":1.1666,"angle":0}],"translate":[{"time":0,"x":0,"y":0,"curve":"stepped"},{"time":1.1666,"x":0,"y":0}],"scale":[{"time":0,"x":1,"y":1,"curve":"stepped"},{"time":1.1666,"x":1,"y":1}]},"left_upper_leg":{"rotate":[{"time":0,"angle":0,"curve":"stepped"},{"time":1.1666,"angle":0}],"translate":[{"time":0,"x":0,"y":0,"curve":"stepped"},{"time":1.1666,"x":0,"y":0}],"scale":[{"time":0,"x":1,"y":1,"curve":"stepped"},{"time":1.1666,"x":1,"y":1}]},"neck":{"rotate":[{"time":0,"angle":0,"curve":"stepped"},{"time":1.1666,"angle":0}],"translate":[{"time":0,"x":0,"y":0,"curve":"stepped"},{"time":1.1666,"x":0,"y":0}],"scale":[{"time":0,"x":1,"y":1,"curve":"stepped"},{"time":1.1666,"x":1,"y":1}]},"right_upper_leg":{"rotate":[{"time":0,"angle":0,"curve":"stepped"},{"time":1.1666,"angle":0}],"translate":[{"time":0,"x":0,"y":0,"curve":"stepped"},{"time":1.1666,"x":0,"y":0}],"scale":[{"time":0,"x":1,"y":1,"curve":"stepped"},{"time":1.1666,"x":1,"y":1}]},"torso":{"rotate":[{"time":0,"angle":0,"curve":"stepped"},{"time":1.1666,"angle":0}],"translate":[{"time":0,"x":0,"y":0,"curve":[0.592,0.24,0.75,1]},{"time":0.5833,"x":0,"y":0.74},{"time":1.1666,"x":0,"y":0}],"scale":[{"time":0,"x":1,"y":1,"curve":"stepped"},{"time":1.1666,"x":1,"y":1}]},"head":{"rotate":[{"time":0,"angle":0,"curve":[0.572,0.24,0.77,0.5]},{"time":0.5833,"angle":3.12,"curve":[0.366,0.66,0.709,0.92]},{"time":1.1666,"angle":0}],"translate":[{"time":0,"x":0,"y":0,"curve":"stepped"},{"time":1.1666,"x":0,"y":0}],"scale":[{"time":0,"x":1,"y":1,"curve":"stepped"},{"time":1.1666,"x":1,"y":1}]},"left_arm":{"rotate":[{"time":0,"angle":-31.86,"curve":[0.592,0.24,0.75,1]},{"time":0.5833,"angle":-25.41},{"time":1.1666,"angle":-31.86}],"translate":[{"time":0,"x":2.96,"y":0.84,"curve":"stepped"},{"time":1.1666,"x":2.96,"y":0.84}],"scale":[{"time":0,"x":1,"y":1,"curve":"stepped"},{"time":1.1666,"x":1,"y":1}]},"left_lower_leg":{"rotate":[{"time":0,"angle":0,"curve":"stepped"},{"time":1.1666,"angle":0}],"translate":[{"time":0,"x":0,"y":0,"curve":"stepped"},{"time":1.1666,"x":0,"y":0}],"scale":[{"time":0,"x":1,"y":1,"curve":"stepped"},{"time":1.1666,"x":1,"y":1}]},"right_arm":{"rotate":[{"time":0,"angle":0,"curve":[0.592,0.24,0.75,1]},{"time":0.5833,"angle":-12.13},{"time":1.1666,"angle":0}],"translate":[{"time":0,"x":0,"y":0,"curve":"stepped"},{"time":1.1666,"x":0,"y":0}],"scale":[{"time":0,"x":1,"y":1,"curve":"stepped"},{"time":1.1666,"x":1,"y":1}]},"right_lower_leg":{"rotate":[{"time":0,"angle":0,"curve":"stepped"},{"time":1.1666,"angle":0}],"translate":[{"time":0,"x":0,"y":0,"curve":"stepped"},{"time":1.1666,"x":0,"y":0}],"scale":[{"time":0,"x":1,"y":1,"curve":"stepped"},{"time":1.1666,"x":1,"y":1}]},"left_foot":{"rotate":[{"time":0,"angle":0,"curve":"stepped"},{"time":1.1666,"angle":0}],"translate":[{"time":0,"x":0,"y":0,"curve":"stepped"},{"time":1.1666,"x":0,"y":0}],"scale":[{"time":0,"x":1,"y":1,"curve":"stepped"},{"time":1.1666,"x":1,"y":1}]},"left_hand":{"rotate":[{"time":0,"angle":24.65,"curve":[0.592,0.24,0.75,1]},{"time":0.5833,"angle":32.33},{"time":1.1666,"angle":24.65}],"translate":[{"time":0,"x":0,"y":0,"curve":"stepped"},{"time":1.1666,"x":0,"y":0}],"scale":[{"time":0,"x":1,"y":1,"curve":"stepped"},{"time":1.1666,"x":1,"y":1}]},"right_foot":{"rotate":[{"time":0,"angle":0,"curve":"stepped"},{"time":1.1666,"angle":0}],"translate":[{"time":0,"x":0,"y":0,"curve":"stepped"},{"time":1.1666,"x":0,"y":0}],"scale":[{"time":0,"x":1,"y":1,"curve":"stepped"},{"time":1.1666,"x":1,"y":1}]},"right_hand":{"rotate":[{"time":0,"angle":-28.42,"curve":[0.592,0.24,0.75,1]},{"time":0.5833,"angle":-18.19},{"time":1.1666,"angle":-28.42}],"translate":[{"time":0,"x":0,"y":0,"curve":"stepped"},{"time":1.1666,"x":0,"y":0}],"scale":[{"time":0,"x":1,"y":1,"curve":"stepped"},{"time":1.1666,"x":1,"y":1}]}}},"jump":{"bones":{"root":{"rotate":[{"time":0,"angle":0}],"translate":[{"time":0,"x":0,"y":0}],"scale":[{"time":0,"x":1,"y":1}]},"pelvis":{"rotate":[{"time":0,"angle":0,"curve":"stepped"},{"time":0.3333,"angle":0,"curve":"stepped"},{"time":0.6666,"angle":0,"curve":"stepped"},{"time":1,"angle":0}],"translate":[{"time":0,"x":0,"y":0},{"time":0.3333,"x":0,"y":3.93,"curve":"stepped"},{"time":0.6666,"x":0,"y":3.93,"curve":"stepped"},{"time":1,"x":0,"y":3.93}],"scale":[{"time":0,"x":1,"y":1,"curve":"stepped"},{"time":0.3333,"x":1,"y":1,"curve":"stepped"},{"time":0.6666,"x":1,"y":1,"curve":"stepped"},{"time":1,"x":1,"y":1}]},"left_upper_leg":{"rotate":[{"time":0,"angle":0},{"time":0.3333,"angle":9.32},{"time":0.5,"angle":14.39},{"time":0.6666,"angle":9.32},{"time":0.8333,"angle":14.39},{"time":1,"angle":9.32},{"time":1.1666,"angle":14.39}],"translate":[{"time":0,"x":0,"y":0,"curve":"stepped"},{"time":0.3333,"x":0,"y":0,"curve":"stepped"},{"time":0.6666,"x":0,"y":0,"curve":"stepped"},{"time":1,"x":0,"y":0}],"scale":[{"time":0,"x":1,"y":1,"curve":"stepped"},{"time":0.3333,"x":1,"y":1,"curve":"stepped"},{"time":0.6666,"x":1,"y":1,"curve":"stepped"},{"time":1,"x":1,"y":1}]},"neck":{"rotate":[{"time":0,"angle":0,"curve":"stepped"},{"time":0.3333,"angle":0,"curve":"stepped"},{"time":0.6666,"angle":0,"curve":"stepped"},{"time":1,"angle":0}],"translate":[{"time":0,"x":0,"y":0,"curve":"stepped"},{"time":0.3333,"x":0,"y":0,"curve":"stepped"},{"time":0.6666,"x":0,"y":0,"curve":"stepped"},{"time":1,"x":0,"y":0}],"scale":[{"time":0,"x":1,"y":1,"curve":"stepped"},{"time":0.3333,"x":1,"y":1,"curve":"stepped"},{"time":0.6666,"x":1,"y":1,"curve":"stepped"},{"time":1,"x":1,"y":1}]},"right_upper_leg":{"rotate":[{"time":0,"angle":0,"curve":"stepped"},{"time":0.3333,"angle":0,"curve":"stepped"},{"time":0.6666,"angle":0,"curve":"stepped"},{"time":1,"angle":0}],"translate":[{"time":0,"x":0,"y":0,"curve":"stepped"},{"time":0.3333,"x":0,"y":0,"curve":"stepped"},{"time":0.6666,"x":0,"y":0,"curve":"stepped"},{"time":1,"x":0,"y":0}],"scale":[{"time":0,"x":1,"y":1,"curve":"stepped"},{"time":0.3333,"x":1,"y":1,"curve":"stepped"},{"time":0.6666,"x":1,"y":1,"curve":"stepped"},{"time":1,"x":1,"y":1}]},"torso":{"rotate":[{"time":0,"angle":0,"curve":"stepped"},{"time":0.3333,"angle":0,"curve":"stepped"},{"time":0.6666,"angle":0,"curve":"stepped"},{"time":1,"angle":0}],"translate":[{"time":0,"x":0,"y":0,"curve":"stepped"},{"time":0.3333,"x":0,"y":0,"curve":"stepped"},{"time":0.6666,"x":0,"y":0,"curve":"stepped"},{"time":1,"x":0,"y":0}],"scale":[{"time":0,"x":1,"y":1,"curve":"stepped"},{"time":0.3333,"x":1,"y":1,"curve":"stepped"},{"time":0.6666,"x":1,"y":1,"curve":"stepped"},{"time":1,"x":1,"y":1}]},"head":{"rotate":[{"time":0,"angle":0},{"time":0.3333,"angle":11.35},{"time":0.6666,"angle":7.03},{"time":1,"angle":8.66}],"translate":[{"time":0,"x":0,"y":0,"curve":"stepped"},{"time":0.3333,"x":0,"y":0,"curve":"stepped"},{"time":0.6666,"x":0,"y":0,"curve":"stepped"},{"time":1,"x":0,"y":0}],"scale":[{"time":0,"x":1,"y":1,"curve":"stepped"},{"time":0.3333,"x":1,"y":1,"curve":"stepped"},{"time":0.6666,"x":1,"y":1,"curve":"stepped"},{"time":1,"x":1,"y":1}]},"left_arm":{"rotate":[{"time":0,"angle":0},{"time":0.3333,"angle":32.05},{"time":0.5,"angle":26.74},{"time":0.6666,"angle":32.05},{"time":0.8333,"angle":26.74},{"time":1,"angle":32.05},{"time":1.1666,"angle":26.74}],"translate":[{"time":0,"x":0,"y":0,"curve":"stepped"},{"time":0.3333,"x":0,"y":0,"curve":"stepped"},{"time":0.6666,"x":0,"y":0,"curve":"stepped"},{"time":1,"x":0,"y":0}],"scale":[{"time":0,"x":1,"y":1,"curve":"stepped"},{"time":0.3333,"x":1,"y":1,"curve":"stepped"},{"time":0.6666,"x":1,"y":1,"curve":"stepped"},{"time":1,"x":1,"y":1}]},"left_lower_leg":{"rotate":[{"time":0,"angle":0,"curve":"stepped"},{"time":0.3333,"angle":0,"curve":"stepped"},{"time":0.6666,"angle":0,"curve":"stepped"},{"time":1,"angle":0}],"translate":[{"time":0,"x":0,"y":0,"curve":"stepped"},{"time":0.3333,"x":0,"y":0,"curve":"stepped"},{"time":0.6666,"x":0,"y":0,"curve":"stepped"},{"time":1,"x":0,"y":0}],"scale":[{"time":0,"x":1,"y":1,"curve":"stepped"},{"time":0.3333,"x":1,"y":1,"curve":"stepped"},{"time":0.6666,"x":1,"y":1,"curve":"stepped"},{"time":1,"x":1,"y":1}]},"right_arm":{"rotate":[{"time":0,"angle":0},{"time":0.3333,"angle":-35.69},{"time":0.5,"angle":-32.86},{"time":0.6666,"angle":-35.69},{"time":0.8333,"angle":-32.86},{"time":1,"angle":-35.69},{"time":1.1666,"angle":-32.86}],"translate":[{"time":0,"x":0,"y":0,"curve":"stepped"},{"time":0.3333,"x":0,"y":0,"curve":"stepped"},{"time":0.6666,"x":0,"y":0,"curve":"stepped"},{"time":1,"x":0,"y":0}],"scale":[{"time":0,"x":1,"y":1,"curve":"stepped"},{"time":0.3333,"x":1,"y":1,"curve":"stepped"},{"time":0.6666,"x":1,"y":1,"curve":"stepped"},{"time":1,"x":1,"y":1}]},"right_lower_leg":{"rotate":[{"time":0,"angle":0,"curve":"stepped"},{"time":0.3333,"angle":0},{"time":0.5,"angle":-11.7},{"time":0.6666,"angle":0},{"time":0.8333,"angle":-11.7},{"time":1,"angle":0},{"time":1.1666,"angle":-11.7}],"translate":[{"time":0,"x":0,"y":0,"curve":"stepped"},{"time":0.3333,"x":0,"y":0,"curve":"stepped"},{"time":0.6666,"x":0,"y":0,"curve":"stepped"},{"time":1,"x":0,"y":0}],"scale":[{"time":0,"x":1,"y":1,"curve":"stepped"},{"time":0.3333,"x":1,"y":1,"curve":"stepped"},{"time":0.6666,"x":1,"y":1,"curve":"stepped"},{"time":1,"x":1,"y":1}]},"left_foot":{"rotate":[{"time":0,"angle":0},{"time":0.3333,"angle":-20.23,"curve":"stepped"},{"time":0.6666,"angle":-20.23,"curve":"stepped"},{"time":1,"angle":-20.23}],"translate":[{"time":0,"x":0,"y":0,"curve":"stepped"},{"time":0.3333,"x":0,"y":0,"curve":"stepped"},{"time":0.6666,"x":0,"y":0,"curve":"stepped"},{"time":1,"x":0,"y":0}],"scale":[{"time":0,"x":1,"y":1,"curve":"stepped"},{"time":0.3333,"x":1,"y":1,"curve":"stepped"},{"time":0.6666,"x":1,"y":1,"curve":"stepped"},{"time":1,"x":1,"y":1}]},"left_hand":{"rotate":[{"time":0,"angle":0,"curve":"stepped"},{"time":0.3333,"angle":0,"curve":"stepped"},{"time":0.6666,"angle":0,"curve":"stepped"},{"time":1,"angle":0}],"translate":[{"time":0,"x":0,"y":0,"curve":"stepped"},{"time":0.3333,"x":0,"y":0,"curve":"stepped"},{"time":0.6666,"x":0,"y":0,"curve":"stepped"},{"time":1,"x":0,"y":0}],"scale":[{"time":0,"x":1,"y":1,"curve":"stepped"},{"time":0.3333,"x":1,"y":1,"curve":"stepped"},{"time":0.6666,"x":1,"y":1,"curve":"stepped"},{"time":1,"x":1,"y":1}]},"right_foot":{"rotate":[{"time":0,"angle":0},{"time":0.3333,"angle":-36.63,"curve":"stepped"},{"time":0.6666,"angle":-36.63,"curve":"stepped"},{"time":1,"angle":-36.63}],"translate":[{"time":0,"x":0,"y":0,"curve":"stepped"},{"time":0.3333,"x":0,"y":0,"curve":"stepped"},{"time":0.6666,"x":0,"y":0,"curve":"stepped"},{"time":1,"x":0,"y":0}],"scale":[{"time":0,"x":1,"y":1,"curve":"stepped"},{"time":0.3333,"x":1,"y":1,"curve":"stepped"},{"time":0.6666,"x":1,"y":1,"curve":"stepped"},{"time":1,"x":1,"y":1}]},"right_hand":{"rotate":[{"time":0,"angle":0},{"time":0.3333,"angle":-22.04,"curve":"stepped"},{"time":0.6666,"angle":-22.04,"curve":"stepped"},{"time":1,"angle":-22.04}],"translate":[{"time":0,"x":0,"y":0,"curve":"stepped"},{"time":0.3333,"x":0,"y":0,"curve":"stepped"},{"time":0.6666,"x":0,"y":0,"curve":"stepped"},{"time":1,"x":0,"y":0}],"scale":[{"time":0,"x":1,"y":1,"curve":"stepped"},{"time":0.3333,"x":1,"y":1,"curve":"stepped"},{"time":0.6666,"x":1,"y":1,"curve":"stepped"},{"time":1,"x":1,"y":1}]}}},"object_push":{"bones":{"root":{"rotate":[{"time":0,"angle":0,"curve":"stepped"},{"time":1.3333,"angle":0}],"translate":[{"time":0,"x":0,"y":0,"curve":"stepped"},{"time":1.3333,"x":0,"y":0}],"scale":[{"time":0,"x":1,"y":1,"curve":"stepped"},{"time":1.3333,"x":1,"y":1}]},"pelvis":{"rotate":[{"time":0,"angle":-11.38,"curve":"stepped"},{"time":1.3333,"angle":-11.38}],"translate":[{"time":0,"x":0,"y":2},{"time":0.3333,"x":0,"y":0},{"time":0.6666,"x":0,"y":3},{"time":1,"x":0,"y":0},{"time":1.3333,"x":0,"y":2}],"scale":[{"time":0,"x":1,"y":1,"curve":"stepped"},{"time":1.3333,"x":1,"y":1}]},"left_upper_leg":{"rotate":[{"time":0,"angle":-41.9},{"time":0.6666,"angle":32.99},{"time":1.3333,"angle":-41.9}],"translate":[{"time":0,"x":0,"y":0,"curve":"stepped"},{"time":1.3333,"x":0,"y":0}],"scale":[{"time":0,"x":1,"y":1,"curve":"stepped"},{"time":1.3333,"x":1,"y":1}]},"neck":{"rotate":[{"time":0,"angle":0.65,"curve":"stepped"},{"time":1.3333,"angle":0.65}],"translate":[{"time":0,"x":0,"y":0,"curve":"stepped"},{"time":1.3333,"x":0,"y":0}],"scale":[{"time":0,"x":1,"y":1,"curve":"stepped"},{"time":1.3333,"x":1,"y":1}]},"right_upper_leg":{"rotate":[{"time":0,"angle":46.87},{"time":0.6666,"angle":-1.47},{"time":1.3333,"angle":46.87}],"translate":[{"time":0,"x":0,"y":0,"curve":"stepped"},{"time":1.3333,"x":0,"y":0}],"scale":[{"time":0,"x":1,"y":1,"curve":"stepped"},{"time":1.3333,"x":1,"y":1}]},"torso":{"rotate":[{"time":0,"angle":0,"curve":"stepped"},{"time":1.3333,"angle":0}],"translate":[{"time":0,"x":0,"y":0,"curve":"stepped"},{"time":1.3333,"x":0,"y":0}],"scale":[{"time":0,"x":1,"y":1,"curve":"stepped"},{"time":1.3333,"x":1,"y":1}]},"head":{"rotate":[{"time":0,"angle":4.39},{"time":0.6666,"angle":10.76},{"time":1.3333,"angle":4.39}],"translate":[{"time":0,"x":0,"y":0,"curve":"stepped"},{"time":1.3333,"x":0,"y":0}],"scale":[{"time":0,"x":1,"y":1,"curve":"stepped"},{"time":1.3333,"x":1,"y":1}]},"left_arm":{"rotate":[{"time":0,"angle":0,"curve":"stepped"},{"time":1.3333,"angle":0}],"translate":[{"time":0,"x":0,"y":0,"curve":"stepped"},{"time":1.3333,"x":0,"y":0}],"scale":[{"time":0,"x":1,"y":1,"curve":"stepped"},{"time":1.3333,"x":1,"y":1}]},"left_lower_leg":{"rotate":[{"time":0,"angle":0,"curve":"stepped"},{"time":1.3333,"angle":0}],"translate":[{"time":0,"x":0,"y":0,"curve":"stepped"},{"time":1.3333,"x":0,"y":0}],"scale":[{"time":0,"x":1,"y":1,"curve":"stepped"},{"time":1.3333,"x":1,"y":1}]},"right_arm":{"rotate":[{"time":0,"angle":64.23,"curve":"stepped"},{"time":1.3333,"angle":64.23}],"translate":[{"time":0,"x":0,"y":0,"curve":"stepped"},{"time":1.3333,"x":0,"y":0}],"scale":[{"time":0,"x":1,"y":1,"curve":"stepped"},{"time":1.3333,"x":1,"y":1}]},"right_lower_leg":{"rotate":[{"time":0,"angle":0},{"time":0.6666,"angle":-9.34},{"time":1.3333,"angle":0}],"translate":[{"time":0,"x":0,"y":0,"curve":"stepped"},{"time":1.3333,"x":0,"y":0}],"scale":[{"time":0,"x":1,"y":1,"curve":"stepped"},{"time":1.3333,"x":1,"y":1}]},"left_foot":{"rotate":[{"time":0,"angle":0.94},{"time":0.3333,"angle":0.58},{"time":0.6666,"angle":-3.92},{"time":1,"angle":5.54},{"time":1.3333,"angle":0.94}],"translate":[{"time":0,"x":0,"y":0,"curve":"stepped"},{"time":0.6666,"x":0,"y":0,"curve":"stepped"},{"time":1.3333,"x":0,"y":0}],"scale":[{"time":0,"x":1,"y":1,"curve":"stepped"},{"time":0.6666,"x":1,"y":1,"curve":"stepped"},{"time":1.3333,"x":1,"y":1}]},"left_hand":{"rotate":[{"time":0,"angle":0,"curve":"stepped"},{"time":1.3333,"angle":0}],"translate":[{"time":0,"x":0,"y":0,"curve":"stepped"},{"time":1.3333,"x":0,"y":0}],"scale":[{"time":0,"x":1,"y":1,"curve":"stepped"},{"time":1.3333,"x":1,"y":1}]},"right_foot":{"rotate":[{"time":0,"angle":0},{"time":0.6666,"angle":-9.92},{"time":1,"angle":-3.91},{"time":1.3333,"angle":0}],"translate":[{"time":0,"x":0,"y":0,"curve":"stepped"},{"time":1.3333,"x":0,"y":0}],"scale":[{"time":0,"x":1,"y":1,"curve":"stepped"},{"time":1.3333,"x":1,"y":1}]},"right_hand":{"rotate":[{"time":0,"angle":0,"curve":"stepped"},{"time":1.3333,"angle":0}],"translate":[{"time":0,"x":0,"y":0,"curve":"stepped"},{"time":1.3333,"x":0,"y":0}],"scale":[{"time":0,"x":1,"y":1,"curve":"stepped"},{"time":1.3333,"x":1,"y":1}]}}},"run":{"bones":{"root":{"rotate":[{"time":0,"angle":0,"curve":"stepped"},{"time":0.6666,"angle":0}],"translate":[{"time":0,"x":0,"y":0,"curve":"stepped"},{"time":0.6666,"x":0,"y":0}],"scale":[{"time":0,"x":1,"y":1,"curve":"stepped"},{"time":0.6666,"x":1,"y":1}]},"pelvis":{"rotate":[{"time":0,"angle":0,"curve":"stepped"},{"time":0.6666,"angle":0}],"translate":[{"time":0,"x":0,"y":7},{"time":0.1666,"x":0,"y":0},{"time":0.3333,"x":0,"y":8},{"time":0.5,"x":0,"y":0},{"time":0.6666,"x":0,"y":7}],"scale":[{"time":0,"x":1,"y":1,"curve":"stepped"},{"time":0.6666,"x":1,"y":1}]},"left_upper_leg":{"rotate":[{"time":0,"angle":15.3},{"time":0.3333,"angle":-14.33},{"time":0.6666,"angle":15.3}],"translate":[{"time":0,"x":0,"y":0,"curve":"stepped"},{"time":0.6666,"x":0,"y":0}],"scale":[{"time":0,"x":1,"y":1,"curve":"stepped"},{"time":0.6666,"x":1,"y":1}]},"neck":{"rotate":[{"time":0,"angle":0,"curve":"stepped"},{"time":0.6666,"angle":0}],"translate":[{"time":0,"x":0,"y":0,"curve":"stepped"},{"time":0.6666,"x":0,"y":0}],"scale":[{"time":0,"x":1,"y":1,"curve":"stepped"},{"time":0.6666,"x":1,"y":1}]},"right_upper_leg":{"rotate":[{"time":0,"angle":-10.89},{"time":0.3333,"angle":44.14},{"time":0.6666,"angle":-10.89}],"translate":[{"time":0,"x":0,"y":0,"curve":"stepped"},{"time":0.6666,"x":0,"y":0}],"scale":[{"time":0,"x":1,"y":1,"curve":"stepped"},{"time":0.6666,"x":1,"y":1}]},"torso":{"rotate":[{"time":0,"angle":0,"curve":"stepped"},{"time":0.6666,"angle":0}],"translate":[{"time":0,"x":0,"y":0,"curve":"stepped"},{"time":0.6666,"x":0,"y":0}],"scale":[{"time":0,"x":1,"y":1,"curve":"stepped"},{"time":0.6666,"x":1,"y":1}]},"head":{"rotate":[{"time":0,"angle":4.45},{"time":0.1666,"angle":0},{"time":0.3333,"angle":5.02},{"time":0.5,"angle":0},{"time":0.6666,"angle":4.45}],"translate":[{"time":0,"x":0,"y":0,"curve":"stepped"},{"time":0.6666,"x":0,"y":0}],"scale":[{"time":0,"x":1,"y":1,"curve":"stepped"},{"time":0.6666,"x":1,"y":1}]},"left_arm":{"rotate":[{"time":0,"angle":24.93},{"time":0.3333,"angle":-21.9},{"time":0.6666,"angle":24.93}],"translate":[{"time":0,"x":0,"y":0,"curve":"stepped"},{"time":0.6666,"x":0,"y":0}],"scale":[{"time":0,"x":1,"y":1,"curve":"stepped"},{"time":0.6666,"x":1,"y":1}]},"left_lower_leg":{"rotate":[{"time":0,"angle":1.96},{"time":0.3333,"angle":-21.06},{"time":0.6666,"angle":1.96}],"translate":[{"time":0,"x":0,"y":0,"curve":"stepped"},{"time":0.3333,"x":0,"y":0,"curve":"stepped"},{"time":0.6666,"x":0,"y":0}],"scale":[{"time":0,"x":1,"y":1,"curve":"stepped"},{"time":0.3333,"x":1,"y":1,"curve":"stepped"},{"time":0.6666,"x":1,"y":1}]},"right_arm":{"rotate":[{"time":0,"angle":-24.48},{"time":0.3333,"angle":57.53},{"time":0.6666,"angle":-24.48}],"translate":[{"time":0,"x":0,"y":0,"curve":"stepped"},{"time":0.6666,"x":0,"y":0}],"scale":[{"time":0,"x":1,"y":1,"curve":"stepped"},{"time":0.6666,"x":1,"y":1}]},"right_lower_leg":{"rotate":[{"time":0,"angle":-20.26},{"time":0.3333,"angle":-22.44},{"time":0.6666,"angle":-20.26}],"translate":[{"time":0,"x":0,"y":0,"curve":"stepped"},{"time":0.6666,"x":0,"y":0}],"scale":[{"time":0,"x":1,"y":1,"curve":"stepped"},{"time":0.6666,"x":1,"y":1}]},"left_foot":{"rotate":[{"time":0,"angle":0},{"time":0.3333,"angle":6.96},{"time":0.6666,"angle":0}],"translate":[{"time":0,"x":0,"y":0,"curve":"stepped"},{"time":0.6666,"x":0,"y":0}],"scale":[{"time":0,"x":1,"y":1,"curve":"stepped"},{"time":0.6666,"x":1,"y":1}]},"left_hand":{"rotate":[{"time":0,"angle":13.07},{"time":0.3333,"angle":26.88},{"time":0.6666,"angle":13.07}],"translate":[{"time":0,"x":0,"y":0,"curve":"stepped"},{"time":0.6666,"x":0,"y":0}],"scale":[{"time":0,"x":1,"y":1,"curve":"stepped"},{"time":0.6666,"x":1,"y":1}]},"right_foot":{"rotate":[{"time":0,"angle":0,"curve":"stepped"},{"time":0.6666,"angle":0}],"translate":[{"time":0,"x":0,"y":0,"curve":"stepped"},{"time":0.6666,"x":0,"y":0}],"scale":[{"time":0,"x":1,"y":1,"curve":"stepped"},{"time":0.6666,"x":1,"y":1}]},"right_hand":{"rotate":[{"time":0,"angle":-19.74},{"time":0.3333,"angle":4.8},{"time":0.6666,"angle":-19.74}],"translate":[{"time":0,"x":0,"y":0,"curve":"stepped"},{"time":0.6666,"x":0,"y":0}],"scale":[{"time":0,"x":1,"y":1,"curve":"stepped"},{"time":0.6666,"x":1,"y":1}]}}}}}